pca_scenery-0.1.17.dist-info/licenses/LICENSE
scenery/__init__.py
scenery/cli.py
scenery/commands.py
scenery/common.py
scenery/core.py
scenery/django_utils.py
scenery/inspect_code.py
scenery/main.py
scenery/manifest.py
scenery/manifest_parser.py
scenery/method_builder.py
scenery/py.typed
scenery/response_checker.py
scenery/set_up_handler.py
pca_scenery-0.1.17.dist-info/METADATA
pca_scenery-0.1.17.dist-info/WHEEL
pca_scenery-0.1.17.dist-info/entry_points.txt
pca_scenery-0.1.17.dist-info/top_level.txt
pca_scenery-0.1.17.dist-info/RECORD
