Metadata-Version: 2.4
Name: pca-scenery
Version: 0.1.17
Summary: Versatile integration tests for web app views
Author: Etienne Madinier
Maintainer: Etienne Madinier
License: MIT License
Project-URL: Homepage, https://pointcarre.app
Project-URL: Repository, https://framagit.org/pointcarre.tech/pca-scenery
Keywords: test,integration,django,view,app
Classifier: Development Status :: 4 - Beta
Classifier: Intended Audience :: Developers
Classifier: Topic :: Software Development :: Testing
Classifier: Programming Language :: Python :: 3
Classifier: Framework :: Django :: 4.2
Classifier: Operating System :: OS Independent
Classifier: License :: OSI Approved :: MIT License
Requires-Python: >=3.11
License-File: LICENSE
Requires-Dist: beautifulsoup4==4.13.4
Requires-Dist: python-dotenv==1.1.1
Requires-Dist: pyyaml==6.0.1
Requires-Dist: selenium==4.27.1
Requires-Dist: requests==2.32.3
Requires-Dist: rich==14.0.0
Provides-Extra: django
Requires-Dist: django==4.2.7; extra == "django"
Provides-Extra: fastapi
Requires-Dist: fastapi[standard]==0.115.13; extra == "fastapi"
Provides-Extra: dev
Requires-Dist: build==1.2.2.post1; extra == "dev"
Requires-Dist: django==4.2.7; extra == "dev"
Requires-Dist: fastapi[standard]==0.115.13; extra == "dev"
Requires-Dist: mkdocs==1.6.1; extra == "dev"
Requires-Dist: mkdocs-material==9.6.15; extra == "dev"
Requires-Dist: mkdocstrings==0.29.1; extra == "dev"
Requires-Dist: mkdocstrings-python==1.16.12; extra == "dev"
Requires-Dist: mypy==1.16.1; extra == "dev"
Requires-Dist: ruff==0.12.2; extra == "dev"
Requires-Dist: twine==6.1.0; extra == "dev"
Dynamic: license-file
